[{"dependency":"@1024pix/ember-cli-notifications","drift":0,"pulse":0.2245037645448323,"releases":0,"major":0,"minor":0,"patch":0,"available":"N/A"},{"dependency":"@1024pix/ember-testing-library","drift":0,"pulse":0.2026009582477755,"releases":0,"major":0,"minor":0,"patch":0,"available":"N/A"},{"dependency":"@1024pix/eslint-config","drift":0,"pulse":0.13689253935660506,"releases":0,"major":0,"minor":0,"patch":0,"available":"N/A"},{"dependency":"@1024pix/pix-ui","drift":0.07665982203969883,"pulse":0.04106776180698152,"releases":5,"major":1,"minor":0,"patch":4,"available":"42.0.4"},{"dependency":"@1024pix/stylelint-config","drift":0,"pulse":0.13689253935660506,"releases":0,"major":0,"minor":0,"patch":0,"available":"N/A"},{"dependency":"@babel/eslint-parser","drift":0,"pulse":0.10951403148528405,"releases":0,"major":0,"minor":0,"patch":0,"available":"8.0.0-alpha.5"},{"dependency":"@ember/optional-features","drift":0,"pulse":3.3976728268309375,"releases":0,"major":0,"minor":0,"patch":0,"available":"N/A"},{"dependency":"@ember/test-helpers","drift":0,"pulse":0.1697467488021903,"releases":0,"major":0,"minor":0,"patch":0,"available":"N/A"},{"dependency":"@embroider/compat","drift":0,"pulse":0.030116358658453114,"releases":0,"major":0,"minor":0,"patch":0,"available":"N/A"},{"dependency":"@embroider/core","drift":0,"pulse":0.030116358658453114,"releases":0,"major":0,"minor":0,"patch":0,"available":"3.4.4-unstable.ecb0185"},{"dependency":"@embroider/webpack","drift":0,"pulse":0.030116358658453114,"releases":0,"major":0,"minor":0,"patch":0,"available":"3.2.2-unstable.efd9117"},{"dependency":"@formatjs/intl","drift":0.17248459958932238,"pulse":0.010951403148528405,"releases":2,"major":0,"minor":0,"patch":2,"available":"2.9.11"},{"dependency":"@fortawesome/ember-fontawesome","drift":0,"pulse":0.35592060232717315,"releases":0,"major":0,"minor":0,"patch":0,"available":"N/A"},{"dependency":"@fortawesome/fontawesome-svg-core","drift":0,"pulse":0.13963039014373715,"releases":0,"major":0,"minor":0,"patch":0,"available":"N/A"},{"dependency":"@fortawesome/free-brands-svg-icons","drift":0,"pulse":0.13963039014373715,"releases":0,"major":0,"minor":0,"patch":0,"available":"N/A"},{"dependency":"@fortawesome/free-regular-svg-icons","drift":0,"pulse":0.13963039014373715,"releases":0,"major":0,"minor":0,"patch":0,"available":"N/A"},{"dependency":"@fortawesome/free-solid-svg-icons","drift":0,"pulse":0.13963039014373715,"releases":0,"major":0,"minor":0,"patch":0,"available":"N/A"},{"dependency":"@glimmer/component","drift":0,"pulse":1.3716632443531827,"releases":0,"major":0,"minor":0,"patch":0,"available":"2.0.0-beta.21"},{"dependency":"@glimmer/tracking","drift":0,"pulse":1.3716632443531827,"releases":0,"major":0,"minor":0,"patch":0,"available":"2.0.0-beta.21"},{"dependency":"dayjs","drift":0,"pulse":0.33675564681724846,"releases":0,"major":0,"minor":0,"patch":0,"available":"2.0.0-alpha.4"},{"dependency":"ember-api-actions","drift":0,"pulse":3.7973990417522243,"releases":0,"major":0,"minor":0,"patch":0,"available":"N/A"},{"dependency":"ember-auto-import","drift":0,"pulse":0.07939767282683094,"releases":0,"major":0,"minor":0,"patch":0,"available":"N/A"},{"dependency":"ember-cli-app-version","drift":0,"pulse":0.5995893223819302,"releases":0,"major":0,"minor":0,"patch":0,"available":"N/A"},{"dependency":"ember-cli-babel","drift":0,"pulse":0.2792607802874743,"releases":0,"major":0,"minor":0,"patch":0,"available":"N/A"},{"dependency":"ember-cli-dependency-checker","drift":0,"pulse":0.5995893223819302,"releases":0,"major":0,"minor":0,"patch":0,"available":"N/A"},{"dependency":"ember-cli-htmlbars","drift":0,"pulse":0.4517453798767967,"releases":0,"major":0,"minor":0,"patch":0,"available":"N/A"},{"dependency":"ember-cli-inject-live-reload","drift":0,"pulse":2.6009582477754964,"releases":0,"major":0,"minor":0,"patch":0,"available":"N/A"},{"dependency":"ember-cli-matomo-tag-manager","drift":0,"pulse":2.839151266255989,"releases":0,"major":0,"minor":0,"patch":0,"available":"N/A"},{"dependency":"ember-cli-mirage","drift":0,"pulse":0.25735797399041754,"releases":0,"major":0,"minor":0,"patch":0,"available":"N/A"},{"dependency":"ember-cli-sass","drift":0,"pulse":1.7357973990417521,"releases":0,"major":0,"minor":0,"patch":0,"available":"N/A"},{"dependency":"ember-cli-showdown","drift":0.5503080082135524,"pulse":0.0027378507871321013,"releases":1,"major":1,"minor":0,"patch":0,"available":"8.0.0"},{"dependency":"ember-cli","drift":0,"pulse":0.08487337440109514,"releases":0,"major":0,"minor":0,"patch":0,"available":"5.6.0-beta.0"},{"dependency":"ember-composable-helpers","drift":0,"pulse":2.1190965092402463,"releases":0,"major":0,"minor":0,"patch":0,"available":"N/A"},{"dependency":"ember-concurrency","drift":0,"pulse":0.4079397672826831,"releases":0,"major":0,"minor":0,"patch":0,"available":"N/A"},{"dependency":"ember-cp-validations","drift":0,"pulse":0.1971252566735113,"releases":0,"major":0,"minor":0,"patch":0,"available":"N/A"},{"dependency":"ember-data","drift":1.757700205338809,"pulse":0.12867898699520877,"releases":45,"major":1,"minor":15,"patch":29,"available":"5.3.0"},{"dependency":"ember-dayjs","drift":0,"pulse":0.6078028747433265,"releases":0,"major":0,"minor":0,"patch":0,"available":"N/A"},{"dependency":"ember-exam","drift":1.9219712525667352,"pulse":0.06023271731690623,"releases":1,"major":1,"minor":0,"patch":0,"available":"9.0.0"},{"dependency":"ember-fetch","drift":0,"pulse":1.4099931553730323,"releases":0,"major":0,"minor":0,"patch":0,"available":"N/A"},{"dependency":"ember-file-upload","drift":0.11772758384668036,"pulse":0.0027378507871321013,"releases":1,"major":1,"minor":0,"patch":0,"available":"9.0.0"},{"dependency":"ember-flatpickr","drift":0.8870636550308009,"pulse":0.010951403148528405,"releases":3,"major":2,"minor":0,"patch":1,"available":"6.0.0"},{"dependency":"ember-intl","drift":0,"pulse":0.10677618069815195,"releases":0,"major":0,"minor":0,"patch":0,"available":"N/A"},{"dependency":"ember-load-initializers","drift":0,"pulse":3.2032854209445585,"releases":0,"major":0,"minor":0,"patch":0,"available":"N/A"},{"dependency":"ember-modifier","drift":0,"pulse":0.8952772073921971,"releases":0,"major":0,"minor":0,"patch":0,"available":"N/A"},{"dependency":"ember-page-title","drift":0.1861738535249829,"pulse":0.03285420944558522,"releases":1,"major":0,"minor":1,"patch":0,"available":"8.2.0"},{"dependency":"ember-qunit","drift":0,"pulse":0.216290212183436,"releases":0,"major":0,"minor":0,"patch":0,"available":"N/A"},{"dependency":"ember-resolver","drift":0,"pulse":0.432580424366872,"releases":0,"major":0,"minor":0,"patch":0,"available":"N/A"},{"dependency":"ember-simple-auth","drift":0,"pulse":0.4243668720054757,"releases":0,"major":0,"minor":0,"patch":0,"available":"N/A"},{"dependency":"ember-source","drift":0.4490075290896646,"pulse":0.008213552361396304,"releases":8,"major":1,"minor":5,"patch":2,"available":"5.5.0"},{"dependency":"ember-template-lint-plugin-prettier","drift":0,"pulse":0.5229295003422314,"releases":0,"major":0,"minor":0,"patch":0,"available":"N/A"},{"dependency":"ember-template-lint","drift":0,"pulse":0.16427104722792607,"releases":0,"major":0,"minor":0,"patch":0,"available":"N/A"},{"dependency":"ember-test-selectors","drift":0,"pulse":2.543463381245722,"releases":0,"major":0,"minor":0,"patch":0,"available":"N/A"},{"dependency":"ember-toggle","drift":0,"pulse":1.9630390143737166,"releases":0,"major":0,"minor":0,"patch":0,"available":"N/A"},{"dependency":"ember-truth-helpers","drift":0,"pulse":0.3586584531143053,"releases":0,"major":0,"minor":0,"patch":0,"available":"N/A"},{"dependency":"eslint-config-prettier","drift":0,"pulse":0.13415468856947296,"releases":0,"major":0,"minor":0,"patch":0,"available":"N/A"},{"dependency":"eslint-plugin-ember","drift":0.08487337440109514,"pulse":0.019164955509924708,"releases":1,"major":1,"minor":0,"patch":0,"available":"12.0.0"},{"dependency":"eslint-plugin-i18n-json","drift":0,"pulse":1.352498288843258,"releases":0,"major":0,"minor":0,"patch":0,"available":"N/A"},{"dependency":"eslint-plugin-node","drift":0,"pulse":3.813826146475017,"releases":0,"major":0,"minor":0,"patch":0,"available":"N/A"},{"dependency":"eslint-plugin-prettier","drift":0.04380561259411362,"pulse":0.030116358658453114,"releases":1,"major":0,"minor":0,"patch":1,"available":"5.1.3"},{"dependency":"eslint-plugin-qunit","drift":0,"pulse":0.2874743326488706,"releases":0,"major":0,"minor":0,"patch":0,"available":"N/A"},{"dependency":"eslint","drift":0,"pulse":0.02190280629705681,"releases":0,"major":0,"minor":0,"patch":0,"available":"9.0.0-alpha.1"},{"dependency":"loader.js","drift":0,"pulse":5.776865160848733,"releases":0,"major":0,"minor":0,"patch":0,"available":"N/A"},{"dependency":"lodash","drift":0,"pulse":2.9130732375085557,"releases":0,"major":0,"minor":0,"patch":0,"available":"N/A"},{"dependency":"npm-run-all","drift":0,"pulse":5.155373032169747,"releases":0,"major":0,"minor":0,"patch":0,"available":"N/A"},{"dependency":"p-queue","drift":0,"pulse":0.10403832991101986,"releases":0,"major":0,"minor":0,"patch":0,"available":"N/A"},{"dependency":"prettier","drift":0.10403832991101986,"pulse":0.008213552361396304,"releases":5,"major":0,"minor":1,"patch":4,"available":"3.2.4"},{"dependency":"query-string","drift":0,"pulse":1.0841889117043122,"releases":0,"major":0,"minor":0,"patch":0,"available":"N/A"},{"dependency":"qunit-dom","drift":0,"pulse":0.2737850787132101,"releases":0,"major":0,"minor":0,"patch":0,"available":"N/A"},{"dependency":"qunit","drift":0,"pulse":0.3258042436687201,"releases":0,"major":0,"minor":0,"patch":0,"available":"N/A"},{"dependency":"sass","drift":0.2299794661190965,"pulse":0.008213552361396304,"releases":3,"major":0,"minor":1,"patch":2,"available":"1.70.0"},{"dependency":"sinon","drift":0,"pulse":0.2190280629705681,"releases":0,"major":0,"minor":0,"patch":0,"available":"N/A"},{"dependency":"stylelint","drift":0.10403832991101986,"pulse":0.0027378507871321013,"releases":2,"major":0,"minor":2,"patch":0,"available":"16.2.0"},{"dependency":"tracked-built-ins","drift":0,"pulse":0.32854209445585214,"releases":0,"major":0,"minor":0,"patch":0,"available":"N/A"},{"dependency":"webpack","drift":0,"pulse":0.27104722792607805,"releases":0,"major":0,"minor":0,"patch":0,"available":"N/A"}]