[{"dependency":"@eslint/js","drift":-0.38329911019849416,"pulse":0.03285420944558522,"releases":3,"major":1,"minor":2,"patch":0,"available":"10.0.0"},{"dependency":"@sentry/node","drift":0.13963039014373715,"pulse":0.0054757015742642025,"releases":11,"major":0,"minor":9,"patch":2,"available":"8.54.0"},{"dependency":"@stylistic/eslint-plugin-js","drift":0.13415468856947296,"pulse":0.019164955509924708,"releases":3,"major":1,"minor":1,"patch":1,"available":"3.0.1"},{"dependency":"axios","drift":0,"pulse":0.17248459958932238,"releases":0,"major":0,"minor":0,"patch":0,"available":"N/A"},{"dependency":"bull-repl","drift":0,"pulse":0.9582477754962354,"releases":0,"major":0,"minor":0,"patch":0,"available":"N/A"},{"dependency":"bull","drift":0.12867898699520877,"pulse":0.13415468856947296,"releases":1,"major":0,"minor":0,"patch":1,"available":"4.16.5"},{"dependency":"bunyan","drift":0,"pulse":4.076659822039699,"releases":6,"major":1,"minor":0,"patch":5,"available":"2.0.5"},{"dependency":"chai-as-promised","drift":0,"pulse":0.2026009582477755,"releases":0,"major":0,"minor":0,"patch":0,"available":"N/A"},{"dependency":"chai","drift":0,"pulse":0.2874743326488706,"releases":0,"major":0,"minor":0,"patch":0,"available":"N/A"},{"dependency":"check-engine","drift":0,"pulse":0.36960985626283366,"releases":0,"major":0,"minor":0,"patch":0,"available":"N/A"},{"dependency":"dotenv","drift":0,"pulse":0.17522245037645448,"releases":0,"major":0,"minor":0,"patch":0,"available":"N/A"},{"dependency":"eslint-plugin-mocha","drift":0,"pulse":0.5256673511293635,"releases":0,"major":0,"minor":0,"patch":0,"available":"N/A"},{"dependency":"eslint-plugin-n","drift":0.02737850787132101,"pulse":0.12867898699520877,"releases":1,"major":0,"minor":0,"patch":1,"available":"17.15.1"},{"dependency":"eslint-plugin-yml","drift":0,"pulse":0.1834360027378508,"releases":0,"major":0,"minor":0,"patch":0,"available":"N/A"},{"dependency":"eslint","drift":0.11225188227241616,"pulse":0.03285420944558522,"releases":2,"major":0,"minor":2,"patch":0,"available":"9.19.0"},{"dependency":"execa","drift":0,"pulse":0.16427104722792607,"releases":0,"major":0,"minor":0,"patch":0,"available":"N/A"},{"dependency":"husky","drift":0,"pulse":0.216290212183436,"releases":0,"major":0,"minor":0,"patch":0,"available":"N/A"},{"dependency":"lodash","drift":0,"pulse":3.9589322381930185,"releases":0,"major":0,"minor":0,"patch":0,"available":"N/A"},{"dependency":"mocha-junit-reporter","drift":0,"pulse":1.571526351813826,"releases":0,"major":0,"minor":0,"patch":0,"available":"N/A"},{"dependency":"mocha","drift":0.08213552361396304,"pulse":0.09582477754962354,"releases":2,"major":0,"minor":1,"patch":1,"available":"11.1.0"},{"dependency":"moment","drift":0,"pulse":1.111567419575633,"releases":0,"major":0,"minor":0,"patch":0,"available":"N/A"},{"dependency":"nock","drift":0.2080766598220397,"pulse":0.03285420944558522,"releases":1,"major":1,"minor":0,"patch":0,"available":"14.0.0"},{"dependency":"pg-connection-string","drift":0,"pulse":0.3860369609856263,"releases":0,"major":0,"minor":0,"patch":0,"available":"N/A"},{"dependency":"pg-format","drift":0,"pulse":7.964407939767283,"releases":0,"major":0,"minor":0,"patch":0,"available":"N/A"},{"dependency":"pg","drift":0,"pulse":0.28473648186173856,"releases":0,"major":0,"minor":0,"patch":0,"available":"N/A"},{"dependency":"proxyquire","drift":0,"pulse":5.486652977412731,"releases":0,"major":0,"minor":0,"patch":0,"available":"N/A"},{"dependency":"sinon-chai","drift":0,"pulse":0.5338809034907598,"releases":0,"major":0,"minor":0,"patch":0,"available":"N/A"},{"dependency":"sinon","drift":0,"pulse":0.39698836413415467,"releases":0,"major":0,"minor":0,"patch":0,"available":"N/A"},{"dependency":"tmp-promise","drift":0,"pulse":3.2799452429842573,"releases":0,"major":0,"minor":0,"patch":0,"available":"N/A"}]