[{"dependency":"@1024pix/oppsy","drift":0,"pulse":0.999315537303217,"releases":0,"major":0,"minor":0,"patch":0,"available":"N/A"},{"dependency":"@adminjs/hapi","drift":0,"pulse":1.6563997262149213,"releases":0,"major":0,"minor":0,"patch":0,"available":"N/A"},{"dependency":"@adminjs/sequelize","drift":0,"pulse":1.6180698151950719,"releases":0,"major":0,"minor":0,"patch":0,"available":"N/A"},{"dependency":"@babel/eslint-parser","drift":0.9253935660506503,"pulse":0.04380561259411362,"releases":10,"major":0,"minor":3,"patch":7,"available":"7.28.0"},{"dependency":"@babel/plugin-syntax-import-assertions","drift":1.1143052703627652,"pulse":0.04380561259411362,"releases":7,"major":0,"minor":3,"patch":4,"available":"7.27.1"},{"dependency":"@hapi/boom","drift":0,"pulse":2.431211498973306,"releases":0,"major":0,"minor":0,"patch":0,"available":"N/A"},{"dependency":"@hapi/cookie","drift":0,"pulse":2.431211498973306,"releases":0,"major":0,"minor":0,"patch":0,"available":"N/A"},{"dependency":"@hapi/hapi","drift":0.917180013689254,"pulse":0.36960985626283366,"releases":5,"major":0,"minor":1,"patch":4,"available":"21.4.0"},{"dependency":"@hapi/inert","drift":0,"pulse":2.349075975359343,"releases":0,"major":0,"minor":0,"patch":0,"available":"N/A"},{"dependency":"@hapi/vision","drift":0,"pulse":1.9548254620123204,"releases":0,"major":0,"minor":0,"patch":0,"available":"N/A"},{"dependency":"@sentry/node","drift":0.37782340862423,"pulse":0.0027378507871321013,"releases":42,"major":0,"minor":37,"patch":5,"available":"9.40.0"},{"dependency":"adminjs","drift":0.8186173853524983,"pulse":0.008213552361396304,"releases":4,"major":0,"minor":0,"patch":4,"available":"7.8.17"},{"dependency":"airtable","drift":0,"pulse":1.9219712525667352,"releases":0,"major":0,"minor":0,"patch":0,"available":"N/A"},{"dependency":"axios-cookiejar-support","drift":0.22176591375770022,"pulse":0.0054757015742642025,"releases":2,"major":0,"minor":0,"patch":2,"available":"6.0.4"},{"dependency":"axios","drift":0.27104722792607805,"pulse":0.09308692676249145,"releases":4,"major":0,"minor":2,"patch":2,"available":"1.10.0"},{"dependency":"base-x","drift":0,"pulse":0.36413415468856947,"releases":0,"major":0,"minor":0,"patch":0,"available":"N/A"},{"dependency":"blipp","drift":0,"pulse":4.657084188911704,"releases":0,"major":0,"minor":0,"patch":0,"available":"N/A"},{"dependency":"bull","drift":0.919917864476386,"pulse":0.5804243668720055,"releases":18,"major":0,"minor":4,"patch":14,"available":"4.16.5"},{"dependency":"countries-list","drift":0.405201916495551,"pulse":0.9637234770704997,"releases":1,"major":0,"minor":0,"patch":1,"available":"3.1.1"},{"dependency":"dotenv","drift":1.3826146475017111,"pulse":0.024640657084188913,"releases":9,"major":1,"minor":4,"patch":4,"available":"17.2.0"},{"dependency":"eslint-plugin-mocha","drift":0.8186173853524983,"pulse":0.15058179329226556,"releases":2,"major":1,"minor":1,"patch":0,"available":"11.1.0"},{"dependency":"eslint","drift":0.919917864476386,"pulse":0.019164955509924708,"releases":27,"major":0,"minor":22,"patch":5,"available":"9.31.0"},{"dependency":"fast-csv","drift":0,"pulse":0.7364818617385352,"releases":0,"major":0,"minor":0,"patch":0,"available":"N/A"},{"dependency":"file-saver","drift":0,"pulse":4.659822039698836,"releases":0,"major":0,"minor":0,"patch":0,"available":"N/A"},{"dependency":"flush-write-stream","drift":0,"pulse":6.439425051334703,"releases":0,"major":0,"minor":0,"patch":0,"available":"N/A"},{"dependency":"form-data","drift":0.11225188227241616,"pulse":0,"releases":1,"major":0,"minor":0,"patch":1,"available":"4.0.4"},{"dependency":"globals","drift":0.09856262833675565,"pulse":0.04654346338124572,"releases":1,"major":0,"minor":1,"patch":0,"available":"16.3.0"},{"dependency":"googleapis","drift":0.10951403148528405,"pulse":0.008213552361396304,"releases":2,"major":2,"minor":0,"patch":0,"available":"153.0.0"},{"dependency":"hapi-pino","drift":1.5770020533880904,"pulse":2.195756331279945,"releases":14,"major":4,"minor":7,"patch":3,"available":"12.1.0"},{"dependency":"hapi-sentry","drift":0,"pulse":1.5003422313483916,"releases":0,"major":0,"minor":0,"patch":0,"available":"4.0.1-2"},{"dependency":"joi","drift":0.2108145106091718,"pulse":1.0787132101300478,"releases":4,"major":0,"minor":1,"patch":3,"available":"17.13.3"},{"dependency":"js-crypto-random","drift":0,"pulse":1.809719370294319,"releases":0,"major":0,"minor":0,"patch":0,"available":"N/A"},{"dependency":"jsonapi-serializer","drift":0,"pulse":1.8316221765913758,"releases":0,"major":0,"minor":0,"patch":0,"available":"N/A"},{"dependency":"knex","drift":0,"pulse":1.6125941136208077,"releases":0,"major":0,"minor":0,"patch":0,"available":"N/A"},{"dependency":"lodash","drift":0,"pulse":4.405201916495551,"releases":0,"major":0,"minor":0,"patch":0,"available":"N/A"},{"dependency":"micromatch","drift":0,"pulse":0.9007529089664613,"releases":0,"major":0,"minor":0,"patch":0,"available":"N/A"},{"dependency":"nock","drift":1.2566735112936345,"pulse":0.019164955509924708,"releases":6,"major":1,"minor":0,"patch":5,"available":"14.0.5"},{"dependency":"node-cache","drift":0,"pulse":5.045859000684462,"releases":0,"major":0,"minor":0,"patch":0,"available":"N/A"},{"dependency":"nodemon","drift":1.163586584531143,"pulse":0.23545516769336072,"releases":10,"major":0,"minor":0,"patch":10,"available":"3.1.10"},{"dependency":"nyc","drift":4.301163586584531,"pulse":0.8295687885010267,"releases":2,"major":1,"minor":1,"patch":0,"available":"17.1.0"},{"dependency":"p-map","drift":0.6735112936344969,"pulse":0.6160164271047228,"releases":1,"major":0,"minor":0,"patch":1,"available":"7.0.3"},{"dependency":"papaparse","drift":0.30390143737166325,"pulse":0.16427104722792607,"releases":1,"major":0,"minor":0,"patch":1,"available":"5.5.3"},{"dependency":"parse-multipart-data","drift":0,"pulse":2.839151266255989,"releases":0,"major":0,"minor":0,"patch":0,"available":"N/A"},{"dependency":"pg-query-stream","drift":1.2320328542094456,"pulse":0.057494866529774126,"releases":17,"major":0,"minor":5,"patch":12,"available":"4.10.3"},{"dependency":"pg","drift":1.2320328542094456,"pulse":0.057494866529774126,"releases":17,"major":0,"minor":5,"patch":12,"available":"8.16.3"},{"dependency":"phrase-js","drift":0.4134154688569473,"pulse":0,"releases":2,"major":0,"minor":2,"patch":0,"available":"3.5.0"},{"dependency":"pino-pretty","drift":0.6433949349760438,"pulse":0.6844626967830253,"releases":8,"major":2,"minor":4,"patch":2,"available":"13.0.0"},{"dependency":"pino","drift":1.1143052703627652,"pulse":0.16700889801505817,"releases":11,"major":1,"minor":8,"patch":2,"available":"9.7.0"},{"dependency":"progress","drift":0,"pulse":6.617385352498289,"releases":0,"major":0,"minor":0,"patch":0,"available":"N/A"},{"dependency":"qs","drift":0.8569472963723477,"pulse":0.5065023956194388,"releases":6,"major":0,"minor":2,"patch":4,"available":"6.14.0"},{"dependency":"sequelize","drift":0.9938398357289527,"pulse":0.3066392881587953,"releases":5,"major":0,"minor":0,"patch":5,"available":"6.37.7"},{"dependency":"showdown","drift":0,"pulse":3.24435318275154,"releases":0,"major":0,"minor":0,"patch":0,"available":"N/A"},{"dependency":"split2","drift":0,"pulse":2.3134839151266258,"releases":0,"major":0,"minor":0,"patch":0,"available":"N/A"},{"dependency":"tough-cookie","drift":1.7357973990417521,"pulse":0.2108145106091718,"releases":5,"major":1,"minor":1,"patch":3,"available":"5.1.2"},{"dependency":"url-regex-safe","drift":0,"pulse":1.9247091033538672,"releases":0,"major":0,"minor":0,"patch":0,"available":"N/A"},{"dependency":"vitest","drift":0.038329911019849415,"pulse":0.008213552361396304,"releases":3,"major":0,"minor":0,"patch":3,"available":"3.2.4"},{"dependency":"yargs","drift":2.080766598220397,"pulse":0.14236824093086928,"releases":1,"major":1,"minor":0,"patch":0,"available":"18.0.0"}]