[{"dependency":"@1024pix/pix-ui","drift":0.4490075290896646,"pulse":0.0027378507871321013,"releases":77,"major":3,"minor":39,"patch":35,"available":"55.23.1"},{"dependency":"@antfu/eslint-config","drift":0.38329911019849416,"pulse":0.01642710472279261,"releases":25,"major":0,"minor":15,"patch":10,"available":"4.16.1"},{"dependency":"@nuxt/content","drift":0.676249144421629,"pulse":0.02190280629705681,"releases":13,"major":1,"minor":6,"patch":6,"available":"3.6.1"},{"dependency":"@playwright/test","drift":0.6433949349760438,"pulse":0,"releases":9,"major":0,"minor":5,"patch":4,"available":"1.53.1"},{"dependency":"@types/node","drift":0.6433949349760438,"pulse":0,"releases":79,"major":1,"minor":5,"patch":73,"available":"24.0.7"},{"dependency":"axios","drift":0.783025325119781,"pulse":0.038329911019849415,"releases":9,"major":0,"minor":3,"patch":6,"available":"1.10.0"},{"dependency":"eslint","drift":0.6516084873374401,"pulse":0.0027378507871321013,"releases":18,"major":0,"minor":16,"patch":2,"available":"9.30.0"},{"dependency":"nuxt","drift":0.4380561259411362,"pulse":0.0027378507871321013,"releases":13,"major":0,"minor":2,"patch":11,"available":"3.17.5"},{"dependency":"plyr","drift":0,"pulse":2.2642026009582477,"releases":0,"major":0,"minor":0,"patch":0,"available":"N/A"},{"dependency":"sass","drift":0.5995893223819302,"pulse":0.05201916495550993,"releases":21,"major":0,"minor":9,"patch":12,"available":"1.89.2"},{"dependency":"srt-to-vtt","drift":0,"pulse":6.86652977412731,"releases":0,"major":0,"minor":0,"patch":0,"available":"N/A"},{"dependency":"vitest","drift":0.39698836413415467,"pulse":0.010951403148528405,"releases":15,"major":0,"minor":2,"patch":13,"available":"3.2.4"}]