[{"dependency":"@antfu/eslint-config","drift":0.26283367556468173,"pulse":0.02737850787132101,"releases":30,"major":2,"minor":8,"patch":20,"available":"2.6.1"},{"dependency":"@fontsource/open-sans","drift":0,"pulse":0.057494866529774126,"releases":0,"major":0,"minor":0,"patch":0,"available":"N/A"},{"dependency":"@fontsource/roboto","drift":0,"pulse":0.4216290212183436,"releases":0,"major":0,"minor":0,"patch":0,"available":"N/A"},{"dependency":"@nuxt/content","drift":0,"pulse":0.04106776180698152,"releases":0,"major":0,"minor":0,"patch":0,"available":"N/A"},{"dependency":"@playwright/test","drift":0,"pulse":0,"releases":0,"major":0,"minor":0,"patch":0,"available":"1.41.0-alpha-nov-29-2023"},{"dependency":"@types/node","drift":0,"pulse":0.02190280629705681,"releases":0,"major":0,"minor":0,"patch":0,"available":"N/A"},{"dependency":"axios","drift":0.024640657084188913,"pulse":0.0027378507871321013,"releases":2,"major":0,"minor":0,"patch":2,"available":"1.6.5"},{"dependency":"eslint","drift":0,"pulse":0.02190280629705681,"releases":0,"major":0,"minor":0,"patch":0,"available":"9.0.0-alpha.0"},{"dependency":"nuxt","drift":0.030116358658453114,"pulse":0.0027378507871321013,"releases":1,"major":0,"minor":0,"patch":1,"available":"3.9.1"},{"dependency":"plyr","drift":0,"pulse":0.7885010266940452,"releases":0,"major":0,"minor":0,"patch":0,"available":"N/A"},{"dependency":"sass","drift":0.010951403148528405,"pulse":0.010951403148528405,"releases":1,"major":0,"minor":0,"patch":1,"available":"1.69.7"},{"dependency":"srt-to-vtt","drift":0,"pulse":5.390828199863107,"releases":0,"major":0,"minor":0,"patch":0,"available":"N/A"},{"dependency":"vitest","drift":0.010951403148528405,"pulse":0.0027378507871321013,"releases":2,"major":0,"minor":0,"patch":2,"available":"1.1.3"}]