[{"dependency":"chai-as-promised","drift":0,"pulse":0.3997262149212868,"releases":0,"major":0,"minor":0,"patch":0,"available":"N/A"},{"dependency":"chai","drift":0.4544832306639288,"pulse":0.02737850787132101,"releases":1,"major":0,"minor":0,"patch":1,"available":"5.1.2"},{"dependency":"cron","drift":0.5557837097878165,"pulse":0.010951403148528405,"releases":1,"major":0,"minor":0,"patch":1,"available":"3.1.8"},{"dependency":"mocha","drift":0.2245037645448323,"pulse":0.008213552361396304,"releases":3,"major":0,"minor":1,"patch":2,"available":"10.8.2"},{"dependency":"nock","drift":0,"pulse":0.07118412046543464,"releases":0,"major":0,"minor":0,"patch":0,"available":"14.0.0-beta.15"},{"dependency":"nyc","drift":0,"pulse":0.12320328542094455,"releases":0,"major":0,"minor":0,"patch":0,"available":"N/A"},{"dependency":"scalingo","drift":0,"pulse":1.593429158110883,"releases":0,"major":0,"minor":0,"patch":0,"available":"N/A"},{"dependency":"sinon-chai","drift":0,"pulse":0.2737850787132101,"releases":0,"major":0,"minor":0,"patch":0,"available":"N/A"},{"dependency":"sinon","drift":0.0054757015742642025,"pulse":0.13689253935660506,"releases":3,"major":1,"minor":0,"patch":2,"available":"19.0.2"}]