[{"dependency":"@1024pix/pix-ui","drift":0,"pulse":0,"releases":0,"major":0,"minor":0,"patch":0,"available":"N/A"},{"dependency":"@antfu/eslint-config","drift":0,"pulse":0.07392197125256673,"releases":0,"major":0,"minor":0,"patch":0,"available":"N/A"},{"dependency":"@nuxt/content","drift":0,"pulse":0.01642710472279261,"releases":0,"major":0,"minor":0,"patch":0,"available":"3.0.0-alpha.6"},{"dependency":"@playwright/test","drift":0,"pulse":0,"releases":0,"major":0,"minor":0,"patch":0,"available":"1.49.0-alpha-2024-11-13"},{"dependency":"@types/node","drift":0,"pulse":0.02190280629705681,"releases":0,"major":0,"minor":0,"patch":0,"available":"N/A"},{"dependency":"axios","drift":0,"pulse":0.1998631074606434,"releases":0,"major":0,"minor":0,"patch":0,"available":"N/A"},{"dependency":"eslint","drift":0,"pulse":0.030116358658453114,"releases":0,"major":0,"minor":0,"patch":0,"available":"N/A"},{"dependency":"nuxt","drift":0,"pulse":0.01642710472279261,"releases":0,"major":0,"minor":0,"patch":0,"available":"N/A"},{"dependency":"plyr","drift":0,"pulse":1.6399726214921286,"releases":0,"major":0,"minor":0,"patch":0,"available":"N/A"},{"dependency":"sass","drift":0.030116358658453114,"pulse":0,"releases":1,"major":0,"minor":0,"patch":1,"available":"1.80.7"},{"dependency":"srt-to-vtt","drift":0,"pulse":6.242299794661191,"releases":0,"major":0,"minor":0,"patch":0,"available":"N/A"},{"dependency":"vitest","drift":0,"pulse":0.04106776180698152,"releases":0,"major":0,"minor":0,"patch":0,"available":"N/A"}]