[{"dependency":"@1024pix/ember-testing-library","drift":0,"pulse":0.06570841889117043,"releases":0,"major":0,"minor":0,"patch":0,"available":"N/A"},{"dependency":"@1024pix/eslint-config","drift":0,"pulse":0.25735797399041754,"releases":0,"major":0,"minor":0,"patch":0,"available":"N/A"},{"dependency":"@1024pix/pix-ui","drift":0,"pulse":0.049281314168377825,"releases":0,"major":0,"minor":0,"patch":0,"available":"N/A"},{"dependency":"@1024pix/stylelint-config","drift":0,"pulse":0.030116358658453114,"releases":0,"major":0,"minor":0,"patch":0,"available":"N/A"},{"dependency":"@babel/eslint-parser","drift":0,"pulse":0.02737850787132101,"releases":0,"major":0,"minor":0,"patch":0,"available":"8.0.0-alpha.3"},{"dependency":"@babel/plugin-proposal-decorators","drift":0.05475701574264202,"pulse":0.02737850787132101,"releases":1,"major":0,"minor":1,"patch":0,"available":"7.23.0"},{"dependency":"@ember/optional-features","drift":0,"pulse":3.1074606433949348,"releases":0,"major":0,"minor":0,"patch":0,"available":"N/A"},{"dependency":"@ember/render-modifiers","drift":0,"pulse":0.34770704996577684,"releases":0,"major":0,"minor":0,"patch":0,"available":"N/A"},{"dependency":"@ember/test-helpers","drift":0,"pulse":0.2683093771389459,"releases":0,"major":0,"minor":0,"patch":0,"available":"N/A"},{"dependency":"@embroider/compat","drift":0.17796030116358658,"pulse":0,"releases":2,"major":0,"minor":0,"patch":2,"available":"3.2.3"},{"dependency":"@embroider/core","drift":0.15879534565366188,"pulse":0,"releases":1,"major":0,"minor":1,"patch":0,"available":"3.3.0"},{"dependency":"@embroider/util","drift":0,"pulse":0,"releases":0,"major":0,"minor":0,"patch":0,"available":"1.12.1-unstable.fe69a74"},{"dependency":"@embroider/webpack","drift":0.15879534565366188,"pulse":0,"releases":1,"major":0,"minor":1,"patch":0,"available":"3.2.0"},{"dependency":"@faker-js/faker","drift":0.31211498973305957,"pulse":0.04654346338124572,"releases":1,"major":0,"minor":1,"patch":0,"available":"8.1.0"},{"dependency":"@formatjs/intl-getcanonicallocales","drift":0,"pulse":0.33675564681724846,"releases":0,"major":0,"minor":0,"patch":0,"available":"N/A"},{"dependency":"@formatjs/intl-locale","drift":0,"pulse":0.07392197125256673,"releases":0,"major":0,"minor":0,"patch":0,"available":"N/A"},{"dependency":"@formatjs/intl-pluralrules","drift":0,"pulse":0.07392197125256673,"releases":0,"major":0,"minor":0,"patch":0,"available":"N/A"},{"dependency":"@formatjs/intl","drift":0,"pulse":0.05201916495550993,"releases":0,"major":0,"minor":0,"patch":0,"available":"N/A"},{"dependency":"@fortawesome/ember-fontawesome","drift":0,"pulse":0.06570841889117043,"releases":0,"major":0,"minor":0,"patch":0,"available":"N/A"},{"dependency":"@fortawesome/free-brands-svg-icons","drift":0,"pulse":0.17796030116358658,"releases":0,"major":0,"minor":0,"patch":0,"available":"N/A"},{"dependency":"@fortawesome/free-regular-svg-icons","drift":0,"pulse":0.17796030116358658,"releases":0,"major":0,"minor":0,"patch":0,"available":"N/A"},{"dependency":"@fortawesome/free-solid-svg-icons","drift":0,"pulse":0.17796030116358658,"releases":0,"major":0,"minor":0,"patch":0,"available":"N/A"},{"dependency":"@glimmer/component","drift":0,"pulse":1.08145106091718,"releases":0,"major":0,"minor":0,"patch":0,"available":"2.0.0-beta.21"},{"dependency":"@sentry/ember","drift":0.06844626967830253,"pulse":0.013689253935660506,"releases":5,"major":0,"minor":5,"patch":0,"available":"7.73.0"},{"dependency":"dayjs","drift":0.2190280629705681,"pulse":0.04654346338124572,"releases":1,"major":0,"minor":0,"patch":1,"available":"1.11.10"},{"dependency":"dotenv","drift":0,"pulse":0.30390143737166325,"releases":0,"major":0,"minor":0,"patch":0,"available":"N/A"},{"dependency":"ember-api-actions","drift":0,"pulse":3.5071868583162216,"releases":0,"major":0,"minor":0,"patch":0,"available":"N/A"},{"dependency":"ember-auto-import","drift":0,"pulse":0.5037645448323066,"releases":0,"major":0,"minor":0,"patch":0,"available":"N/A"},{"dependency":"ember-cli-app-version","drift":0,"pulse":0.30937713894592744,"releases":0,"major":0,"minor":0,"patch":0,"available":"N/A"},{"dependency":"ember-cli-autoprefixer","drift":0,"pulse":1.9055441478439425,"releases":0,"major":0,"minor":0,"patch":0,"available":"N/A"},{"dependency":"ember-cli-babel","drift":0.10403832991101986,"pulse":0.02737850787132101,"releases":2,"major":0,"minor":1,"patch":1,"available":"8.1.0"},{"dependency":"ember-cli-clipboard","drift":0,"pulse":0.12320328542094455,"releases":0,"major":0,"minor":0,"patch":0,"available":"N/A"},{"dependency":"ember-cli-dependency-checker","drift":0,"pulse":0.30937713894592744,"releases":0,"major":0,"minor":0,"patch":0,"available":"N/A"},{"dependency":"ember-cli-head","drift":0,"pulse":2.3627652292950034,"releases":0,"major":0,"minor":0,"patch":0,"available":"N/A"},{"dependency":"ember-cli-htmlbars","drift":0,"pulse":0.16153319644079397,"releases":0,"major":0,"minor":0,"patch":0,"available":"N/A"},{"dependency":"ember-cli-inject-live-reload","drift":0,"pulse":2.3107460643394937,"releases":0,"major":0,"minor":0,"patch":0,"available":"N/A"},{"dependency":"ember-cli-matomo-tag-manager","drift":0,"pulse":2.5516769336071183,"releases":0,"major":0,"minor":0,"patch":0,"available":"N/A"},{"dependency":"ember-cli-mirage","drift":1.702943189596167,"pulse":0.0054757015742642025,"releases":1,"major":1,"minor":0,"patch":0,"available":"3.0.0"},{"dependency":"ember-cli-sass","drift":0,"pulse":1.4455852156057496,"releases":0,"major":0,"minor":0,"patch":0,"available":"N/A"},{"dependency":"ember-cli","drift":0.06570841889117043,"pulse":0.04654346338124572,"releases":1,"major":0,"minor":1,"patch":0,"available":"5.3.0"},{"dependency":"ember-cookies","drift":0,"pulse":0.46269678302532513,"releases":0,"major":0,"minor":0,"patch":0,"available":"N/A"},{"dependency":"ember-data","drift":1.757700205338809,"pulse":0.008213552361396304,"releases":42,"major":1,"minor":15,"patch":26,"available":"5.3.0"},{"dependency":"ember-dayjs","drift":0,"pulse":0.31759069130732376,"releases":0,"major":0,"minor":0,"patch":0,"available":"N/A"},{"dependency":"ember-exam","drift":0,"pulse":1.6947296372347707,"releases":0,"major":0,"minor":0,"patch":0,"available":"N/A"},{"dependency":"ember-fetch","drift":0,"pulse":1.1197809719370295,"releases":0,"major":0,"minor":0,"patch":0,"available":"N/A"},{"dependency":"ember-intl","drift":0,"pulse":0.04654346338124572,"releases":0,"major":0,"minor":0,"patch":0,"available":"N/A"},{"dependency":"ember-keyboard","drift":0,"pulse":0.13963039014373715,"releases":0,"major":0,"minor":0,"patch":0,"available":"N/A"},{"dependency":"ember-load-initializers","drift":0,"pulse":2.9130732375085557,"releases":0,"major":0,"minor":0,"patch":0,"available":"N/A"},{"dependency":"ember-modifier","drift":0,"pulse":0.6050650239561944,"releases":0,"major":0,"minor":0,"patch":0,"available":"N/A"},{"dependency":"ember-page-title","drift":0,"pulse":0.13963039014373715,"releases":0,"major":0,"minor":0,"patch":0,"available":"N/A"},{"dependency":"ember-qunit","drift":0,"pulse":0.06570841889117043,"releases":0,"major":0,"minor":0,"patch":0,"available":"N/A"},{"dependency":"ember-resolver","drift":0,"pulse":0.14236824093086928,"releases":0,"major":0,"minor":0,"patch":0,"available":"N/A"},{"dependency":"ember-responsive","drift":0,"pulse":1.5058179329226558,"releases":0,"major":0,"minor":0,"patch":0,"available":"N/A"},{"dependency":"ember-simple-auth","drift":0,"pulse":0.13415468856947296,"releases":0,"major":0,"minor":0,"patch":0,"available":"N/A"},{"dependency":"ember-source","drift":0.216290212183436,"pulse":0.0054757015742642025,"releases":6,"major":1,"minor":3,"patch":2,"available":"5.3.0"},{"dependency":"ember-template-lint-plugin-prettier","drift":0,"pulse":0.2327173169062286,"releases":0,"major":0,"minor":0,"patch":0,"available":"N/A"},{"dependency":"ember-template-lint","drift":0,"pulse":0.15331964407939766,"releases":0,"major":0,"minor":0,"patch":0,"available":"N/A"},{"dependency":"ember-test-selectors","drift":0,"pulse":2.2559890485968515,"releases":0,"major":0,"minor":0,"patch":0,"available":"N/A"},{"dependency":"ember-truth-helpers","drift":0,"pulse":0.06844626967830253,"releases":0,"major":0,"minor":0,"patch":0,"available":"N/A"},{"dependency":"eslint-config-prettier","drift":0,"pulse":0.1697467488021903,"releases":0,"major":0,"minor":0,"patch":0,"available":"N/A"},{"dependency":"eslint-plugin-ember","drift":0,"pulse":0.12320328542094455,"releases":0,"major":0,"minor":0,"patch":0,"available":"N/A"},{"dependency":"eslint-plugin-node","drift":0,"pulse":3.5263518138261465,"releases":0,"major":0,"minor":0,"patch":0,"available":"N/A"},{"dependency":"eslint-plugin-prettier","drift":0,"pulse":0.24093086926762491,"releases":0,"major":0,"minor":0,"patch":0,"available":"N/A"},{"dependency":"eslint-plugin-qunit","drift":0,"pulse":0.27652292950034224,"releases":0,"major":0,"minor":0,"patch":0,"available":"N/A"},{"dependency":"eslint","drift":0.07392197125256673,"pulse":0,"releases":2,"major":0,"minor":2,"patch":0,"available":"8.51.0"},{"dependency":"js-yaml","drift":0.35044490075290896,"pulse":2.4777549623545516,"releases":2,"major":1,"minor":1,"patch":0,"available":"4.1.0"},{"dependency":"jwt-decode","drift":0,"pulse":0.08761122518822724,"releases":0,"major":0,"minor":0,"patch":0,"available":"4.0.0-beta.4"},{"dependency":"loader.js","drift":0,"pulse":5.486652977412731,"releases":0,"major":0,"minor":0,"patch":0,"available":"N/A"},{"dependency":"lodash","drift":0,"pulse":2.622861054072553,"releases":0,"major":0,"minor":0,"patch":0,"available":"N/A"},{"dependency":"miragejs","drift":0,"pulse":0.7392197125256673,"releases":0,"major":0,"minor":0,"patch":0,"available":"N/A"},{"dependency":"npm-run-all","drift":0,"pulse":4.865160848733744,"releases":0,"major":0,"minor":0,"patch":0,"available":"N/A"},{"dependency":"p-queue","drift":0,"pulse":0.09308692676249145,"releases":0,"major":0,"minor":0,"patch":0,"available":"N/A"},{"dependency":"prettier","drift":0,"pulse":0.10403832991101986,"releases":0,"major":0,"minor":0,"patch":0,"available":"N/A"},{"dependency":"qunit-dom","drift":0,"pulse":0,"releases":0,"major":0,"minor":0,"patch":0,"available":"3.0.0-rc.1"},{"dependency":"qunit","drift":0.6652977412731006,"pulse":0.03559206023271732,"releases":1,"major":0,"minor":1,"patch":0,"available":"2.20.0"},{"dependency":"sass","drift":0.13141683778234087,"pulse":0.0027378507871321013,"releases":3,"major":0,"minor":3,"patch":0,"available":"1.69.0"},{"dependency":"showdown","drift":0,"pulse":1.462012320328542,"releases":0,"major":0,"minor":0,"patch":0,"available":"N/A"},{"dependency":"sinon","drift":0.057494866529774126,"pulse":0.0027378507871321013,"releases":1,"major":0,"minor":1,"patch":0,"available":"16.1.0"},{"dependency":"stylelint-order","drift":0,"pulse":0.5859000684462696,"releases":0,"major":0,"minor":0,"patch":0,"available":"N/A"},{"dependency":"stylelint","drift":0,"pulse":0.13415468856947296,"releases":0,"major":0,"minor":0,"patch":0,"available":"N/A"},{"dependency":"webpack","drift":0,"pulse":0.08213552361396304,"releases":0,"major":0,"minor":0,"patch":0,"available":"N/A"},{"dependency":"xss","drift":0,"pulse":1.1389459274469542,"releases":0,"major":0,"minor":0,"patch":0,"available":"N/A"}]