[{"dependency":"chai-as-promised","drift":0,"pulse":0.47913372622298883,"releases":0,"major":0,"minor":0,"patch":0},{"dependency":"chai","drift":0.3340246548525979,"pulse":0.1451090713703909,"releases":6,"major":1,"minor":2,"patch":3,"latest":"6.2.2"},{"dependency":"cron","drift":0.355927910908506,"pulse":0.1807018624612415,"releases":3,"major":0,"minor":1,"patch":2,"latest":"4.4.0"},{"dependency":"mocha","drift":0.1752260484472645,"pulse":0,"releases":3,"major":0,"minor":0,"patch":3,"latest":"11.7.5"},{"dependency":"nock","drift":0.13141953633544837,"pulse":0.010951628027954031,"releases":2,"major":1,"minor":0,"patch":1,"latest":"15.0.0"},{"dependency":"nyc","drift":0,"pulse":1.4045462945851044,"releases":0,"major":0,"minor":0,"patch":0},{"dependency":"scalingo","drift":1.0705216397325064,"pulse":0.021903256055908062,"releases":25,"major":0,"minor":6,"patch":19,"latest":"0.17.11"},{"dependency":"sinon-chai","drift":0,"pulse":0.47913372622298883,"releases":0,"major":0,"minor":0,"patch":0},{"dependency":"sinon","drift":0.7364969848799086,"pulse":0.15332279239135643,"releases":2,"major":1,"minor":0,"patch":1,"latest":"21.0.1"}]