[{"dependency":"@1024pix/ember-api-actions","drift":0,"pulse":0.33401779603011633,"releases":0,"major":0,"minor":0,"patch":0,"available":"N/A"},{"dependency":"@1024pix/ember-matomo-tag-manager","drift":0,"pulse":0.9007529089664613,"releases":0,"major":0,"minor":0,"patch":0,"available":"N/A"},{"dependency":"@1024pix/ember-testing-library","drift":0,"pulse":0.11498973305954825,"releases":0,"major":0,"minor":0,"patch":0,"available":"N/A"},{"dependency":"@1024pix/eslint-plugin","drift":0,"pulse":0.1697467488021903,"releases":0,"major":0,"minor":0,"patch":0,"available":"N/A"},{"dependency":"@1024pix/pix-ui","drift":0,"pulse":0.02190280629705681,"releases":0,"major":0,"minor":0,"patch":0,"available":"N/A"},{"dependency":"@1024pix/stylelint-config","drift":0,"pulse":0.07939767282683094,"releases":0,"major":0,"minor":0,"patch":0,"available":"N/A"},{"dependency":"@babel/eslint-parser","drift":0.0054757015742642025,"pulse":0.13689253935660506,"releases":1,"major":0,"minor":0,"patch":1,"available":"7.25.1"},{"dependency":"@babel/plugin-proposal-decorators","drift":0,"pulse":0.14236824093086928,"releases":0,"major":0,"minor":0,"patch":0,"available":"8.0.0-alpha.12"},{"dependency":"@ember-data/json-api","drift":0,"pulse":0.04106776180698152,"releases":0,"major":0,"minor":0,"patch":0,"available":"5.5.0-alpha.11"},{"dependency":"@ember-data/model","drift":0,"pulse":0.04106776180698152,"releases":0,"major":0,"minor":0,"patch":0,"available":"5.5.0-alpha.11"},{"dependency":"@ember/optional-features","drift":0,"pulse":0.5694729637234771,"releases":0,"major":0,"minor":0,"patch":0,"available":"N/A"},{"dependency":"@ember/render-modifiers","drift":0,"pulse":1.2950034223134839,"releases":0,"major":0,"minor":0,"patch":0,"available":"N/A"},{"dependency":"@ember/test-helpers","drift":0.11498973305954825,"pulse":0.03285420944558522,"releases":5,"major":1,"minor":0,"patch":4,"available":"4.0.4"},{"dependency":"@embroider/compat","drift":0.11772758384668036,"pulse":0.010951403148528405,"releases":1,"major":0,"minor":0,"patch":1,"available":"3.6.1"},{"dependency":"@embroider/core","drift":0.1806981519507187,"pulse":0.010951403148528405,"releases":1,"major":0,"minor":0,"patch":1,"available":"3.4.15"},{"dependency":"@embroider/macros","drift":0.1806981519507187,"pulse":0.010951403148528405,"releases":1,"major":0,"minor":0,"patch":1,"available":"1.16.6"},{"dependency":"@embroider/util","drift":0,"pulse":0.010951403148528405,"releases":0,"major":0,"minor":0,"patch":0,"available":"1.13.3-unstable.f7656a3"},{"dependency":"@embroider/webpack","drift":0.1806981519507187,"pulse":0.010951403148528405,"releases":1,"major":0,"minor":0,"patch":1,"available":"4.0.5"},{"dependency":"@formatjs/intl","drift":0,"pulse":0.33127994524298426,"releases":0,"major":0,"minor":0,"patch":0,"available":"N/A"},{"dependency":"@fortawesome/ember-fontawesome","drift":0,"pulse":1.0130047912388775,"releases":0,"major":0,"minor":0,"patch":0,"available":"N/A"},{"dependency":"@fortawesome/fontawesome-svg-core","drift":0,"pulse":0.1697467488021903,"releases":0,"major":0,"minor":0,"patch":0,"available":"N/A"},{"dependency":"@fortawesome/free-brands-svg-icons","drift":0,"pulse":0.1697467488021903,"releases":0,"major":0,"minor":0,"patch":0,"available":"N/A"},{"dependency":"@fortawesome/free-regular-svg-icons","drift":0,"pulse":0.1697467488021903,"releases":0,"major":0,"minor":0,"patch":0,"available":"N/A"},{"dependency":"@fortawesome/free-solid-svg-icons","drift":0,"pulse":0.1697467488021903,"releases":0,"major":0,"minor":0,"patch":0,"available":"N/A"},{"dependency":"@glimmer/component","drift":0,"pulse":2.028747433264887,"releases":0,"major":0,"minor":0,"patch":0,"available":"2.0.0-beta.21"},{"dependency":"@sentry/ember","drift":0.12867898699520877,"pulse":0.01642710472279261,"releases":10,"major":0,"minor":10,"patch":0,"available":"8.30.0"},{"dependency":"@testing-library/user-event","drift":0,"pulse":0.7173169062286106,"releases":0,"major":0,"minor":0,"patch":0,"available":"N/A"},{"dependency":"buffer","drift":0,"pulse":3.8165639972621492,"releases":0,"major":0,"minor":0,"patch":0,"available":"N/A"},{"dependency":"dayjs","drift":0.09034907597535935,"pulse":0.07392197125256673,"releases":1,"major":0,"minor":0,"patch":1,"available":"1.11.13"},{"dependency":"dotenv","drift":0,"pulse":0.5749486652977412,"releases":0,"major":0,"minor":0,"patch":0,"available":"N/A"},{"dependency":"ember-auto-import","drift":0.2272416153319644,"pulse":0,"releases":1,"major":0,"minor":1,"patch":0,"available":"2.8.0"},{"dependency":"ember-cli-app-version","drift":0,"pulse":0.2683093771389459,"releases":0,"major":0,"minor":0,"patch":0,"available":"N/A"},{"dependency":"ember-cli-autoprefixer","drift":0,"pulse":2.8528405201916494,"releases":0,"major":0,"minor":0,"patch":0,"available":"N/A"},{"dependency":"ember-cli-babel","drift":0,"pulse":0.9363449691991786,"releases":0,"major":0,"minor":0,"patch":0,"available":"N/A"},{"dependency":"ember-cli-clipboard","drift":0,"pulse":0.15879534565366188,"releases":0,"major":0,"minor":0,"patch":0,"available":"N/A"},{"dependency":"ember-cli-dependency-checker","drift":0,"pulse":1.2566735112936345,"releases":0,"major":0,"minor":0,"patch":0,"available":"N/A"},{"dependency":"ember-cli-deprecation-workflow","drift":0.11225188227241616,"pulse":0.07118412046543464,"releases":1,"major":0,"minor":0,"patch":1,"available":"3.0.2"},{"dependency":"ember-cli-htmlbars","drift":0,"pulse":1.108829568788501,"releases":0,"major":0,"minor":0,"patch":0,"available":"N/A"},{"dependency":"ember-cli-inject-live-reload","drift":0,"pulse":3.2580424366872007,"releases":0,"major":0,"minor":0,"patch":0,"available":"N/A"},{"dependency":"ember-cli-mirage","drift":0.5201916495550992,"pulse":0.03559206023271732,"releases":1,"major":0,"minor":0,"patch":1,"available":"3.0.4"},{"dependency":"ember-cli-sass","drift":0,"pulse":2.3928815879534566,"releases":0,"major":0,"minor":0,"patch":0,"available":"N/A"},{"dependency":"ember-cli","drift":0.11498973305954825,"pulse":0.07665982203969883,"releases":1,"major":0,"minor":1,"patch":0,"available":"5.11.0"},{"dependency":"ember-component-css","drift":0,"pulse":2.3600273785078714,"releases":0,"major":0,"minor":0,"patch":0,"available":"1.0.0-alpha.3"},{"dependency":"ember-cookies","drift":0,"pulse":0.6899383983572895,"releases":0,"major":0,"minor":0,"patch":0,"available":"N/A"},{"dependency":"ember-data","drift":0,"pulse":0.04106776180698152,"releases":0,"major":0,"minor":0,"patch":0,"available":"5.5.0-alpha.12"},{"dependency":"ember-dayjs","drift":0,"pulse":0.30390143737166325,"releases":0,"major":0,"minor":0,"patch":0,"available":"N/A"},{"dependency":"ember-eslint-parser","drift":0.1971252566735113,"pulse":0.0027378507871321013,"releases":1,"major":0,"minor":0,"patch":1,"available":"0.5.1"},{"dependency":"ember-exam","drift":0,"pulse":0.7173169062286106,"releases":0,"major":0,"minor":0,"patch":0,"available":"N/A"},{"dependency":"ember-fetch","drift":0,"pulse":2.0670773442847366,"releases":0,"major":0,"minor":0,"patch":0,"available":"N/A"},{"dependency":"ember-intl","drift":0.16427104722792607,"pulse":0.02190280629705681,"releases":2,"major":0,"minor":0,"patch":2,"available":"7.0.6"},{"dependency":"ember-keyboard","drift":1.0212183436002737,"pulse":0.06570841889117043,"releases":2,"major":1,"minor":0,"patch":1,"available":"9.0.1"},{"dependency":"ember-lifeline","drift":0,"pulse":1.3388090349075976,"releases":0,"major":0,"minor":0,"patch":0,"available":"N/A"},{"dependency":"ember-load-initializers","drift":0,"pulse":3.8603696098562628,"releases":0,"major":0,"minor":0,"patch":0,"available":"N/A"},{"dependency":"ember-modifier","drift":0,"pulse":0.2053388090349076,"releases":0,"major":0,"minor":0,"patch":0,"available":"N/A"},{"dependency":"ember-page-title","drift":0,"pulse":0.5174537987679672,"releases":0,"major":0,"minor":0,"patch":0,"available":"N/A"},{"dependency":"ember-qunit","drift":0,"pulse":0.2655715263518138,"releases":0,"major":0,"minor":0,"patch":0,"available":"N/A"},{"dependency":"ember-resolver","drift":1.0869267624914443,"pulse":0,"releases":4,"major":2,"minor":0,"patch":2,"available":"13.0.1"},{"dependency":"ember-responsive","drift":0,"pulse":2.4531143052703626,"releases":0,"major":0,"minor":0,"patch":0,"available":"N/A"},{"dependency":"ember-simple-auth","drift":1.0595482546201231,"pulse":0.019164955509924708,"releases":1,"major":0,"minor":1,"patch":0,"available":"6.1.0"},{"dependency":"ember-source","drift":0.2080766598220397,"pulse":0,"releases":4,"major":0,"minor":2,"patch":2,"available":"5.11.0"},{"dependency":"ember-template-imports","drift":0,"pulse":0.34223134839151265,"releases":0,"major":0,"minor":0,"patch":0,"available":"N/A"},{"dependency":"ember-template-lint-plugin-prettier","drift":0,"pulse":1.1800136892539357,"releases":0,"major":0,"minor":0,"patch":0,"available":"N/A"},{"dependency":"ember-template-lint","drift":0.3531827515400411,"pulse":0.4681724845995893,"releases":1,"major":1,"minor":0,"patch":0,"available":"6.0.0"},{"dependency":"ember-test-selectors","drift":3.055441478439425,"pulse":0.14510609171800137,"releases":1,"major":1,"minor":0,"patch":0,"available":"7.0.0"},{"dependency":"ember-truth-helpers","drift":0,"pulse":1.0157426420260096,"releases":0,"major":0,"minor":0,"patch":0,"available":"N/A"},{"dependency":"eslint-config-prettier","drift":0,"pulse":0.7912388774811773,"releases":0,"major":0,"minor":0,"patch":0,"available":"N/A"},{"dependency":"eslint-plugin-ember","drift":0.24093086926762491,"pulse":0.08213552361396304,"releases":1,"major":0,"minor":1,"patch":0,"available":"12.2.0"},{"dependency":"eslint-plugin-i18n-json","drift":0,"pulse":2.0095824777549622,"releases":0,"major":0,"minor":0,"patch":0,"available":"N/A"},{"dependency":"eslint-plugin-n","drift":0.024640657084188913,"pulse":0.11772758384668036,"releases":1,"major":0,"minor":0,"patch":1,"available":"17.10.2"},{"dependency":"eslint-plugin-prettier","drift":0,"pulse":0.16700889801505817,"releases":0,"major":0,"minor":0,"patch":0,"available":"N/A"},{"dependency":"eslint-plugin-qunit","drift":0.5229295003422314,"pulse":0.07118412046543464,"releases":1,"major":0,"minor":0,"patch":1,"available":"8.1.2"},{"dependency":"eslint","drift":0.5338809034907598,"pulse":0,"releases":14,"major":1,"minor":10,"patch":3,"available":"9.10.0"},{"dependency":"globals","drift":0,"pulse":0.12594113620807665,"releases":0,"major":0,"minor":0,"patch":0,"available":"N/A"},{"dependency":"js-yaml","drift":0.35044490075290896,"pulse":3.4250513347022586,"releases":2,"major":1,"minor":1,"patch":0,"available":"4.1.0"},{"dependency":"jwt-decode","drift":0,"pulse":0.8898015058179329,"releases":0,"major":0,"minor":0,"patch":0,"available":"N/A"},{"dependency":"loader.js","drift":0,"pulse":6.433949349760438,"releases":0,"major":0,"minor":0,"patch":0,"available":"N/A"},{"dependency":"lodash","drift":0,"pulse":3.57015742642026,"releases":0,"major":0,"minor":0,"patch":0,"available":"N/A"},{"dependency":"miragejs","drift":0,"pulse":0.243668720054757,"releases":0,"major":0,"minor":0,"patch":0,"available":"0.2.0-alpha.3"},{"dependency":"npm-run-all2","drift":0.1943874058863792,"pulse":0.008213552361396304,"releases":1,"major":0,"minor":0,"patch":1,"available":"6.2.3"},{"dependency":"p-queue","drift":0,"pulse":0.7611225188227242,"releases":0,"major":0,"minor":0,"patch":0,"available":"N/A"},{"dependency":"plyr","drift":0,"pulse":1.483915126625599,"releases":0,"major":0,"minor":0,"patch":0,"available":"N/A"},{"dependency":"prettier-plugin-ember-template-tag","drift":0,"pulse":0.4544832306639288,"releases":0,"major":0,"minor":0,"patch":0,"available":"N/A"},{"dependency":"prettier","drift":0,"pulse":0.038329911019849415,"releases":0,"major":0,"minor":0,"patch":0,"available":"4.0.0-alpha.10"},{"dependency":"qunit-dom","drift":0,"pulse":0.22176591375770022,"releases":0,"major":0,"minor":0,"patch":0,"available":"N/A"},{"dependency":"qunit","drift":0.07939767282683094,"pulse":0.07665982203969883,"releases":1,"major":0,"minor":1,"patch":0,"available":"2.22.0"},{"dependency":"sass","drift":0.14784394250513347,"pulse":0.03559206023271732,"releases":1,"major":0,"minor":1,"patch":0,"available":"1.78.0"},{"dependency":"showdown","drift":0,"pulse":2.409308692676249,"releases":0,"major":0,"minor":0,"patch":0,"available":"N/A"},{"dependency":"sinon","drift":0.33127994524298426,"pulse":0.008213552361396304,"releases":4,"major":1,"minor":0,"patch":3,"available":"19.0.2"},{"dependency":"stylelint-order","drift":0,"pulse":0.7748117727583846,"releases":0,"major":0,"minor":0,"patch":0,"available":"N/A"},{"dependency":"stylelint","drift":0.12594113620807665,"pulse":0.05475701574264202,"releases":4,"major":0,"minor":2,"patch":2,"available":"16.9.0"},{"dependency":"webpack","drift":0,"pulse":0.06844626967830253,"releases":0,"major":0,"minor":0,"patch":0,"available":"N/A"},{"dependency":"xss","drift":0,"pulse":0.5420944558521561,"releases":0,"major":0,"minor":0,"patch":0,"available":"N/A"}]