[{"dependency":"@1024pix/eslint-config","drift":0,"pulse":0.01642710472279261,"releases":0,"major":0,"minor":0,"patch":0,"available":"N/A"},{"dependency":"@hapi/boom","drift":0,"pulse":1.4428473648186173,"releases":0,"major":0,"minor":0,"patch":0,"available":"N/A"},{"dependency":"@hapi/hapi","drift":0,"pulse":0.10951403148528405,"releases":0,"major":0,"minor":0,"patch":0,"available":"N/A"},{"dependency":"@hapi/inert","drift":0,"pulse":1.3607118412046544,"releases":0,"major":0,"minor":0,"patch":0,"available":"N/A"},{"dependency":"@hapi/vision","drift":0,"pulse":0.9664613278576317,"releases":0,"major":0,"minor":0,"patch":0,"available":"N/A"},{"dependency":"@tsconfig/node-lts-strictest-esm","drift":0,"pulse":1.7111567419575633,"releases":0,"major":0,"minor":0,"patch":0,"available":"N/A"},{"dependency":"@types/bcrypt","drift":0,"pulse":0.7091033538672142,"releases":0,"major":0,"minor":0,"patch":0,"available":"10.0.28-alpha"},{"dependency":"@types/chai","drift":0,"pulse":0.216290212183436,"releases":0,"major":0,"minor":0,"patch":0,"available":"N/A"},{"dependency":"@types/jsonwebtoken","drift":0,"pulse":0.4024640657084189,"releases":0,"major":0,"minor":0,"patch":0,"available":"N/A"},{"dependency":"@types/mocha","drift":0,"pulse":0.08213552361396304,"releases":0,"major":0,"minor":0,"patch":0,"available":"N/A"},{"dependency":"@types/ms","drift":0,"pulse":0.7063655030800822,"releases":0,"major":0,"minor":0,"patch":0,"available":"N/A"},{"dependency":"@types/node","drift":0.030116358658453114,"pulse":0.010951403148528405,"releases":1,"major":0,"minor":0,"patch":1,"available":"20.14.11"},{"dependency":"@types/papaparse","drift":0,"pulse":0.6543463381245722,"releases":0,"major":0,"minor":0,"patch":0,"available":"N/A"},{"dependency":"@types/sinon-chai","drift":0,"pulse":0.7063655030800822,"releases":0,"major":0,"minor":0,"patch":0,"available":"N/A"},{"dependency":"@types/sinon","drift":0,"pulse":0.5311430527036276,"releases":0,"major":0,"minor":0,"patch":0,"available":"N/A"},{"dependency":"@types/yargs","drift":0,"pulse":0.6707734428473648,"releases":0,"major":0,"minor":0,"patch":0,"available":"N/A"},{"dependency":"@typescript-eslint/eslint-plugin","drift":0.019164955509924708,"pulse":0,"releases":1,"major":0,"minor":1,"patch":0,"available":"7.17.0"},{"dependency":"@typescript-eslint/parser","drift":0.019164955509924708,"pulse":0,"releases":1,"major":0,"minor":1,"patch":0,"available":"7.17.0"},{"dependency":"bcrypt","drift":0,"pulse":0.9363449691991786,"releases":0,"major":0,"minor":0,"patch":0,"available":"N/A"},{"dependency":"chai","drift":0.3203285420944558,"pulse":0.2026009582477755,"releases":5,"major":1,"minor":1,"patch":3,"available":"5.1.1"},{"dependency":"depcheck","drift":0,"pulse":0.7638603696098563,"releases":0,"major":0,"minor":0,"patch":0,"available":"N/A"},{"dependency":"dotenv","drift":0,"pulse":0.4216290212183436,"releases":0,"major":0,"minor":0,"patch":0,"available":"N/A"},{"dependency":"eslint-config-prettier","drift":0,"pulse":0.6379192334017796,"releases":0,"major":0,"minor":0,"patch":0,"available":"N/A"},{"dependency":"eslint-plugin-chai-expect","drift":0,"pulse":0.10677618069815195,"releases":0,"major":0,"minor":0,"patch":0,"available":"N/A"},{"dependency":"eslint-plugin-knex","drift":0,"pulse":0.3613963039014374,"releases":0,"major":0,"minor":0,"patch":0,"available":"N/A"},{"dependency":"eslint-plugin-mocha","drift":0,"pulse":0.25735797399041754,"releases":0,"major":0,"minor":0,"patch":0,"available":"N/A"},{"dependency":"eslint-plugin-n","drift":0,"pulse":0.10677618069815195,"releases":0,"major":0,"minor":0,"patch":0,"available":"N/A"},{"dependency":"eslint-plugin-prettier","drift":0.5174537987679672,"pulse":0.013689253935660506,"releases":1,"major":0,"minor":1,"patch":0,"available":"5.2.1"},{"dependency":"eslint-plugin-unicorn","drift":0,"pulse":0.10403832991101986,"releases":0,"major":0,"minor":0,"patch":0,"available":"N/A"},{"dependency":"eslint","drift":0.38329911019849416,"pulse":0.02737850787132101,"releases":9,"major":1,"minor":7,"patch":1,"available":"9.7.0"},{"dependency":"hapi-swagger","drift":0,"pulse":0.5037645448323066,"releases":0,"major":0,"minor":0,"patch":0,"available":"N/A"},{"dependency":"joi","drift":0,"pulse":0.09034907597535935,"releases":0,"major":0,"minor":0,"patch":0,"available":"N/A"},{"dependency":"jsonwebtoken","drift":0,"pulse":0.8952772073921971,"releases":0,"major":0,"minor":0,"patch":0,"available":"N/A"},{"dependency":"knex","drift":0,"pulse":0.6242299794661191,"releases":0,"major":0,"minor":0,"patch":0,"available":"N/A"},{"dependency":"lodash","drift":0,"pulse":3.4168377823408624,"releases":0,"major":0,"minor":0,"patch":0,"available":"N/A"},{"dependency":"mocha","drift":0.049281314168377825,"pulse":0.0054757015742642025,"releases":2,"major":0,"minor":1,"patch":1,"available":"10.7.0"},{"dependency":"moment","drift":0,"pulse":0.5694729637234771,"releases":0,"major":0,"minor":0,"patch":0,"available":"N/A"},{"dependency":"ms","drift":0,"pulse":2.8501026694045173,"releases":0,"major":0,"minor":0,"patch":0,"available":"3.0.0-canary.1"},{"dependency":"nodemon","drift":0,"pulse":0.08761122518822724,"releases":0,"major":0,"minor":0,"patch":0,"available":"N/A"},{"dependency":"npm-run-all2","drift":0,"pulse":0.05201916495550993,"releases":0,"major":0,"minor":0,"patch":0,"available":"N/A"},{"dependency":"papaparse","drift":0,"pulse":1.3333333333333333,"releases":0,"major":0,"minor":0,"patch":0,"available":"N/A"},{"dependency":"pg","drift":0,"pulse":0.13141683778234087,"releases":0,"major":0,"minor":0,"patch":0,"available":"N/A"},{"dependency":"pino-pretty","drift":0,"pulse":0.10951403148528405,"releases":0,"major":0,"minor":0,"patch":0,"available":"N/A"},{"dependency":"pino","drift":0,"pulse":0.019164955509924708,"releases":0,"major":0,"minor":0,"patch":0,"available":"N/A"},{"dependency":"prettier","drift":0,"pulse":0.024640657084188913,"releases":0,"major":0,"minor":0,"patch":0,"available":"4.0.0-alpha.9"},{"dependency":"sinon-chai","drift":0,"pulse":0.19164955509924708,"releases":0,"major":0,"minor":0,"patch":0,"available":"4.0.0-0"},{"dependency":"sinon","drift":0,"pulse":0.1861738535249829,"releases":0,"major":0,"minor":0,"patch":0,"available":"N/A"},{"dependency":"tsx","drift":0,"pulse":0.05201916495550993,"releases":0,"major":0,"minor":0,"patch":0,"available":"N/A"},{"dependency":"typescript","drift":0.057494866529774126,"pulse":0,"releases":1,"major":0,"minor":0,"patch":1,"available":"5.5.4"},{"dependency":"yargs","drift":0,"pulse":1.2375085557837098,"releases":0,"major":0,"minor":0,"patch":0,"available":"N/A"}]